Metadata-Version: 2.1
Name: surlparser
Version: 1.1
Summary: 解析http、https url的一个小工具
Home-page: UNKNOWN
Author: Cooper
Author-email: 734327367@qq.com
License: UNKNOWN
Platform: UNKNOWN
Classifier: Programming Language :: Python :: 3
Classifier: License :: OSI Approved :: MIT License
Classifier: Operating System :: OS Independent
Requires-Python: >=3.6
